napari_cryofibsem_imgproc/__init__.py
napari_cryofibsem_imgproc/_sample_data.py
napari_cryofibsem_imgproc/_widget.py
napari_cryofibsem_imgproc/brightness.py
napari_cryofibsem_imgproc/contrast.py
napari_cryofibsem_imgproc/decharge.py
napari_cryofibsem_imgproc/decurtain.py
napari_cryofibsem_imgproc/denoise.py
napari_cryofibsem_imgproc/medianblur.py
napari_cryofibsem_imgproc/napari.yaml
napari_cryofibsem_imgproc/_tests/__init__.py
napari_cryofibsem_imgproc/_tests/test_sample_data.py
napari_cryofibsem_imgproc/_tests/test_widget.py
napari_cryofibsem_imgproc-0.0.7.dist-info/licenses/LICENSE
napari_cryofibsem_imgproc-0.0.7.dist-info/METADATA
napari_cryofibsem_imgproc-0.0.7.dist-info/WHEEL
napari_cryofibsem_imgproc-0.0.7.dist-info/entry_points.txt
napari_cryofibsem_imgproc-0.0.7.dist-info/top_level.txt
napari_cryofibsem_imgproc-0.0.7.dist-info/RECORD
