Metadata-Version: 2.4
Name: napari-cryofibsem-imgproc
Version: 0.0.7
Summary: A napari plugin for artifact removal, noise reduction, contrast enhancement and stack brightness correction of Cryo-FIB/SEM image stacks.
Author: Shaina V. To
Author-email: shaina.to@radboudumc.nl
License: 
Project-URL: Bug Tracker, https://github.com/EMCRUMC/napari-cryofibsem-imgproc/issues
Project-URL: Documentation, https://github.com/EMCRUMC/napari-cryofibsem-imgproc#README.md
Project-URL: Source Code, https://github.com/EMCRUMC/napari-cryofibsem-imgproc
Project-URL: User Support, https://github.com/EMCRUMC/napari-cryofibsem-imgproc/issues
Classifier: Development Status :: 2 - Pre-Alpha
Classifier: Framework :: napari
Classifier: Intended Audience :: Developers
Classifier: License :: OSI Approved :: Apache Software License
Classifier: Operating System :: OS Independent
Classifier: Programming Language :: Python
Classifier: Programming Language :: Python :: 3
Classifier: Programming Language :: Python :: 3 :: Only
Classifier: Programming Language :: Python :: 3.10
Classifier: Programming Language :: Python :: 3.11
Classifier: Programming Language :: Python :: 3.12
Classifier: Topic :: Scientific/Engineering :: Image Processing
Requires-Python: >=3.10
License-File: LICENSE
Requires-Dist: numpy==1.26.4
Requires-Dist: magicgui
Requires-Dist: scikit-image==0.24.0
Requires-Dist: PyWavelets==1.6.0
Requires-Dist: opencv-python==4.10.0.84
Provides-Extra: testing
Requires-Dist: tox; extra == "testing"
Requires-Dist: pytest; extra == "testing"
Requires-Dist: pytest-cov; extra == "testing"
Requires-Dist: pytest-qt; extra == "testing"
Requires-Dist: napari; extra == "testing"
Requires-Dist: pyqt5; extra == "testing"
Dynamic: license-file
